bjcli/__init__.py
bjcli/__main__.py
bjcli/utils.py
bjcli-1.0.3.dist-info/LICENSE
bjcli-1.0.3.dist-info/METADATA
bjcli-1.0.3.dist-info/WHEEL
bjcli-1.0.3.dist-info/entry_points.txt
bjcli-1.0.3.dist-info/top_level.txt
bjcli-1.0.3.dist-info/RECORD
