Metadata-Version: 2.1
Name: bjcli
Version: 1.0.3
Summary: Simple command line utility to run Bjoern WSGI
Home-page: https://notabug.org/kapustlo/bjcli
Author: Kapustlo
License: UNKNOWN
Keywords: python,bjoern,cli,bjoern-cli,wsgi
Platform: UNKNOWN
Classifier: License :: OSI Approved :: GNU General Public License v3 (GPLv3)
Classifier: Topic :: Internet :: WWW/HTTP :: WSGI :: Server
Classifier: Environment :: Console
Classifier: Environment :: Web Environment
Classifier: Development Status :: 5 - Production/Stable
Classifier: Intended Audience :: Developers
Classifier: Programming Language :: Python :: 3.9
Classifier: Operating System :: Unix
Requires-Python: >=3.9
License-File: LICENSE
Requires-Dist: bjoern
